datetimetools/__init__.py
datetimetools/date_utils.py
dttools-0.1.1.dist-info/METADATA
dttools-0.1.1.dist-info/WHEEL
dttools-0.1.1.dist-info/top_level.txt
dttools-0.1.1.dist-info/RECORD
