Metadata-Version: 2.1
Name: dttools
Version: 0.1.1
Summary: A simple library for common date and time manipulations
Home-page: https://github.com/l4christ/dttools
Author: Emmanuel Ademola
Author-email: ademola.emmanuel383@gmail.com
Classifier: Programming Language :: Python :: 3
Classifier: License :: OSI Approved :: MIT License
Classifier: Operating System :: OS Independent
Requires-Python: >=3.6
Requires-Dist: pytz
